{
    "localeName": "English",
    "stayTop": "Stay on top",
    "listenClipboard": "Listen Clipboard",
    "autoCopy": "Auto Copy",
    "autoPaste": "Auto Paste",
    "incrementalCopy": "Incremental Copy",
    "smartDict": "Smart Dict",
    "translate": "Translate",
    "copySource": "Copy Source",
    "copyResult": "Copy Result",
    "source": "Source",
    "result": "Result",
    "sourceLanguage": "Source Language",
    "targetLanguage": "Target Language",
    "detectLanguage": "Detected Language",
    "clear": "Clear",
    "helpAndUpdate": "Help And Update",
    "exit": "Exit",
    "contrastMode": "Contrast Mode",
    "focusMode": "Focus Mode",
    "switchMode": "Switch Mode",
    "autoHide": "Auto Hide",
    "autoFormat": "Auto Format",
    "autoShow": "Auto Show",
    "settings": "Settings",
    "viewSource": "View Source",
    "localeSetting": "Locale",
    "return": "Return"
}